xlocust_bigquery/__init__.py
xlocust_bigquery/bigquery.py
xlocust_bigquery/bq_client.py
xlocust_bigquery-0.0.5.dist-info/LICENSE.txt
xlocust_bigquery-0.0.5.dist-info/METADATA
xlocust_bigquery-0.0.5.dist-info/WHEEL
xlocust_bigquery-0.0.5.dist-info/top_level.txt
xlocust_bigquery-0.0.5.dist-info/RECORD
